_distutils_hack/__init__.py
_distutils_hack/override.py
backports/__init__.py
backports/tarfile/__init__.py
backports/tarfile/__main__.py
backports/tarfile/compat/__init__.py
backports/tarfile/compat/py38.py
certifi/__init__.py
certifi/__main__.py
certifi/core.py
certifi/py.typed
charset_normalizer/__init__.py
charset_normalizer/__main__.py
charset_normalizer/api.py
charset_normalizer/cd.py
charset_normalizer/constant.py
charset_normalizer/legacy.py
charset_normalizer/md.py
charset_normalizer/models.py
charset_normalizer/py.typed
charset_normalizer/utils.py
charset_normalizer/version.py
charset_normalizer/cli/__init__.py
charset_normalizer/cli/__main__.py
docutils/__init__.py
docutils/__main__.py
docutils/core.py
docutils/examples.py
docutils/frontend.py
docutils/io.py
docutils/nodes.py
docutils/statemachine.py
docutils/languages/__init__.py
docutils/languages/af.py
docutils/languages/ar.py
docutils/languages/ca.py
docutils/languages/cs.py
docutils/languages/da.py
docutils/languages/de.py
docutils/languages/en.py
docutils/languages/eo.py
docutils/languages/es.py
docutils/languages/fa.py
docutils/languages/fi.py
docutils/languages/fr.py
docutils/languages/gl.py
docutils/languages/he.py
docutils/languages/it.py
docutils/languages/ja.py
docutils/languages/ka.py
docutils/languages/ko.py
docutils/languages/lt.py
docutils/languages/lv.py
docutils/languages/nl.py
docutils/languages/pl.py
docutils/languages/pt_br.py
docutils/languages/ru.py
docutils/languages/sk.py
docutils/languages/sv.py
docutils/languages/uk.py
docutils/languages/zh_cn.py
docutils/languages/zh_tw.py
docutils/parsers/__init__.py
docutils/parsers/commonmark_wrapper.py
docutils/parsers/null.py
docutils/parsers/recommonmark_wrapper.py
docutils/parsers/rst/__init__.py
docutils/parsers/rst/roles.py
docutils/parsers/rst/states.py
docutils/parsers/rst/tableparser.py
docutils/parsers/rst/directives/__init__.py
docutils/parsers/rst/directives/admonitions.py
docutils/parsers/rst/directives/body.py
lv_vectordb_gcp-0.6.0.dist-info/LICENSE
lv_vectordb_gcp-0.6.0.dist-info/METADATA
lv_vectordb_gcp-0.6.0.dist-info/WHEEL
lv_vectordb_gcp-0.6.0.dist-info/top_level.txt
lv_vectordb_gcp-0.6.0.dist-info/RECORD
